streamlit_qs/__init__.py
streamlit_qs/py.typed
streamlit_qs-0.3.3.dist-info/LICENSE
streamlit_qs-0.3.3.dist-info/METADATA
streamlit_qs-0.3.3.dist-info/WHEEL
streamlit_qs-0.3.3.dist-info/top_level.txt
streamlit_qs-0.3.3.dist-info/RECORD
