Metadata-Version: 2.1
Name: streamlit-qs
Version: 0.3.3
Summary: A small library to add extra functionality on top of streamlit's st.query_params API
Author-email: Alexander Martin <fauxjunk-1@yahoo.com>
Project-URL: Homepage, https://query-string.streamlit.app/
Project-URL: Repository, https://github.com/Asaurus1/streamlit-qs
Project-URL: Issues, https://github.com/Asaurus1/streamlit-qs/issues
Keywords: streamlit,query,url,query_params,widgets,extension,community,permalink,state,save,data
Classifier: Programming Language :: Python :: 3
Classifier: License :: OSI Approved :: Apache Software License
Classifier: Operating System :: OS Independent
Classifier: Environment :: Web Environment
Classifier: Intended Audience :: Information Technology
Classifier: Intended Audience :: Financial and Insurance Industry
Classifier: Intended Audience :: Science/Research
Classifier: Intended Audience :: Developers
Classifier: Natural Language :: English
Classifier: Topic :: Software Development :: Libraries :: Python Modules
Classifier: Topic :: Utilities
Requires-Python: !=3.9.7,>=3.8
License-File: LICENSE
Requires-Dist: streamlit >=1.30.0
